emmtyper/__init__.py
emmtyper/bin/__init__.py
emmtyper/bin/run_emmtyper.py
emmtyper/data/emm_clusters.csv
emmtyper/data/isPcrPrim.tsv
emmtyper/db/db_metadata.json
emmtyper/db/emm.fna
emmtyper/db/emm.fna.nhr
emmtyper/db/emm.fna.nin
emmtyper/db/emm.fna.nsq
emmtyper/objects/__init__.py
emmtyper/objects/blast.py
emmtyper/objects/clusterer.py
emmtyper/objects/command.py
emmtyper/objects/emm.py
emmtyper/objects/ispcr.py
emmtyper/objects/result_row.py
emmtyper/utilities/__init__.py
emmtyper/utilities/find.py
emmtyper/utilities/make_db.py
emmtyper/utilities/run_blast.py
emmtyper/utilities/run_ispcr.py
emmtyper-0.2.0.dist-info/LICENSE
emmtyper-0.2.0.dist-info/METADATA
emmtyper-0.2.0.dist-info/WHEEL
emmtyper-0.2.0.dist-info/entry_points.txt
emmtyper-0.2.0.dist-info/top_level.txt
emmtyper-0.2.0.dist-info/RECORD
