Metadata-Version: 2.1
Name: emmtyper
Version: 0.2.0
Summary: Streptococcus pyogenes in silico EMM typer
Home-page: https://github.com/MDUPHL/emmtyper
Author: Andre Tan
Author-email: andre.sutanto.91@gmail.com
Maintainer: Bioinformatics @ MDUPHL
Maintainer-email: anders.goncalves@unimelb.edu.au
License: GPL-3.0
Platform: UNKNOWN
Classifier: Development Status :: 4 - Beta
Classifier: Programming Language :: Python :: Implementation :: CPython
Classifier: Intended Audience :: Science/Research
Classifier: License :: OSI Approved :: GNU General Public License v3 (GPLv3)
Classifier: Natural Language :: English
Classifier: Programming Language :: Python :: 3 :: Only
Classifier: Programming Language :: Python :: 3.6
Classifier: Programming Language :: Python :: 3.7
Classifier: Topic :: Scientific/Engineering :: Bio-Informatics
Requires-Python: >=3.6, <4
Requires-Dist: scipy (>=1.1.0)
Requires-Dist: numpy (>=1.15.0)
Requires-Dist: python-dateutil
Requires-Dist: click
